{
  "$schema": "../../../node_modules/ng-packagr/ng-package.schema.json",
  "dest": "../../../dist/external-libraries/weavescope",
  "lib": {
    "entryFile": "src/public-api.ts"
  },
  "whitelistedNonPeerDependencies": [
    "@anyopsos/lib-angular-material",
    "@anyopsos/lib-pipes",
    "@anyopsos/lib-utils",
    "d3-format",
    "d3-scale",
    "d3-scale-chromatic",
    "d3-shape",
    "dagre",
    "filesize",
    "immutable",
    "json-stable-stringify",
    "lodash-es",
    "reselect",
    "reselect-map",
    "weavescope",
    "weaveworks-ui-components"
  ]
}
